cluster365/__init__.py
cluster365/main.py
cluster365-0.1.0.dist-info/METADATA
cluster365-0.1.0.dist-info/WHEEL
cluster365-0.1.0.dist-info/entry_points.txt
cluster365-0.1.0.dist-info/top_level.txt
cluster365-0.1.0.dist-info/RECORD
